Metadata-Version: 2.1
Name: arviz
Version: 0.22.0
Summary: Exploratory analysis of Bayesian models
Home-page: http://github.com/arviz-devs/arviz
Author: ArviZ Developers
License: Apache-2.0
Classifier: Development Status :: 4 - Beta
Classifier: Framework :: Matplotlib
Classifier: Intended Audience :: Science/Research
Classifier: Intended Audience :: Education
Classifier: License :: OSI Approved :: Apache Software License
Classifier: Programming Language :: Python
Classifier: Programming Language :: Python :: 3
Classifier: Programming Language :: Python :: 3.10
Classifier: Programming Language :: Python :: 3.11
Classifier: Programming Language :: Python :: 3.12
Classifier: Topic :: Scientific/Engineering
Classifier: Topic :: Scientific/Engineering :: Visualization
Classifier: Topic :: Scientific/Engineering :: Mathematics
Requires-Python: >=3.10
Provides-Extra: all
Provides-Extra: preview
License-File: LICENSE
